FileBlackHolePy/__init__.py
FileBlackHolePy/fileBlackHole.py
FileBlackHolePy-0.0.1.dist-info/LICENSE
FileBlackHolePy-0.0.1.dist-info/METADATA
FileBlackHolePy-0.0.1.dist-info/WHEEL
FileBlackHolePy-0.0.1.dist-info/top_level.txt
FileBlackHolePy-0.0.1.dist-info/RECORD
