Metadata-Version: 2.1
Name: FileBlackHolePy
Version: 0.0.1
Summary: Python API for FileBlackHole.
Home-page: https://github.com/iLikeTrioxin/FileBlackHolePy/
Author: iLikeTrioxin
Author-email: iLikeTrioxin@protonmail.com
License: GNU Affero General Public License v3
Project-URL: Bug Tracker, https://github.com/iLikeTrioxin/FileBlackHolePy/issues
Classifier: Programming Language :: Python :: 3
Classifier: License :: OSI Approved :: GNU Affero General Public License v3
Classifier: Operating System :: OS Independent
Requires-Python: >=3.6
License-File: LICENSE
Requires-Dist: aiohttp
Requires-Dist: asyncio
